{"entries":[{"playerName":"Server","playerDisplayName":"Server","prefix":"\u0026x\u0026f\u0026b\u0026d\u0026c\u00265\u00266\u0026lɢᴏʟᴅ \u0026x\u0026f\u0026b\u0026d\u0026c\u00265\u00266","suffix":"","playerID":"5e8127e5-646b-36d6-9ff7-ace1050597d8","position":1,"board":"statistic_time_played","type":"DAILY","score":11259.0},{"playerName":"Freemason123","playerDisplayName":"Freemason123","prefix":"\u00267ᴘʟᴀʏᴇʀ \u00267","suffix":"","playerID":"06ec8428-cd4a-3803-8739-45afff5e903e","position":2,"board":"statistic_time_played","type":"DAILY","score":9554.0},{"playerName":"xuesos","playerDisplayName":"xuesos","prefix":"\u00267ᴘʟᴀʏᴇʀ \u00267","suffix":"","playerID":"f97cf6cb-a77b-39dc-b941-c0cf147a0c90","position":3,"board":"statistic_time_played","type":"DAILY","score":7069.0},{"playerName":"hezzllll","playerDisplayName":"hezzllll","prefix":"\u0026x\u0026f\u0026b\u0026d\u0026c\u00265\u00266\u0026lɢᴏʟᴅ \u0026x\u0026f\u0026b\u0026d\u0026c\u00265\u00266","suffix":"","playerID":"d5d6f8cb-fb7e-3f03-9521-f8f3315b8f90","position":4,"board":"statistic_time_played","type":"DAILY","score":6550.0},{"playerName":"geimer_30009121","playerDisplayName":"geimer_30009121","prefix":"\u00267ᴘʟᴀʏᴇʀ \u00267","suffix":"","playerID":"0559633d-2327-33d4-a469-db157d3e1592","position":5,"board":"statistic_time_played","type":"DAILY","score":6444.0},{"playerName":"FoxEdit","playerDisplayName":"FoxEdit","prefix":"\u00267ᴘʟᴀʏᴇʀ \u00267","suffix":"","playerID":"3eb99dc0-980d-32bb-83d2-c826bb8fe3b2","position":6,"board":"statistic_time_played","type":"DAILY","score":4334.0},{"playerName":"Cdznbr","playerDisplayName":"Cdznbr","prefix":"\u00267ᴘʟᴀʏᴇʀ \u00267","suffix":"","playerID":"8f5db8db-d846-30cc-88fc-5716d6132f89","position":7,"board":"statistic_time_played","type":"DAILY","score":2855.0},{"playerName":"Rossi","playerDisplayName":"Rossi","prefix":"\u0026x\u0026f\u0026b\u0026d\u0026c\u00265\u00266\u0026lɢᴏʟᴅ \u0026x\u0026f\u0026b\u0026d\u0026c\u00265\u00266","suffix":"","playerID":"ecbb6f9e-a2ec-376a-b50e-7c0d92a72821","position":8,"board":"statistic_time_played","type":"DAILY","score":1431.0},{"playerName":"Qinenewti","playerDisplayName":"Qinenewti","prefix":"\u0026x\u00269\u0026d\u00269\u0026d\u00269\u0026d\u0026lᴄᴏᴀʟ \u0026x\u00269\u0026d\u00269\u0026d\u00269\u0026d","suffix":"","playerID":"6ce487c7-8c46-31e5-8d92-0cfda4270584","position":9,"board":"statistic_time_played","type":"DAILY","score":1380.0},{"playerName":"warionX","playerDisplayName":"warionX","prefix":"\u00267ᴘʟᴀʏᴇʀ \u00267","suffix":"","playerID":"c34d8c92-3c05-3ac2-885e-7bdf5c0ec5ce","position":10,"board":"statistic_time_played","type":"DAILY","score":470.0}],"meta":{"time":1710802800266,"type":"DAILY","board":"statistic_time_played"}}